myokit/__init__.py
myokit/__main__.py
myokit/_aux.py
myokit/_config.py
myokit/_datablock.py
myokit/_datalog.py
myokit/_err.py
myokit/_expressions.py
myokit/_io.py
myokit/_model_api.py
myokit/_myokit_version.py
myokit/_parsing.py
myokit/_progress.py
myokit/_protocol.py
myokit/_system.py
myokit/_unit.py
myokit/float.py
myokit/pacing.py
myokit/pype.py
myokit/tools.py
myokit/units.py
myokit/_bin/example.mmt
myokit/_bin/gui/find.png
myokit/_bin/gui/icon-datablock-viewer-128.xpm
myokit/_bin/gui/icon-datablock-viewer-16.xpm
myokit/_bin/gui/icon-datablock-viewer-24.xpm
myokit/_bin/gui/icon-datablock-viewer-256.xpm
myokit/_bin/gui/icon-datablock-viewer-32.xpm
myokit/_bin/gui/icon-datablock-viewer-48.xpm
myokit/_bin/gui/icon-datablock-viewer-64.xpm
myokit/_bin/gui/icon-datablock-viewer-96.xpm
myokit/_bin/gui/icon-datablock-viewer.ico
myokit/_bin/gui/icon-datablock-viewer.png
myokit/_bin/gui/icon-ide-128.xpm
myokit/_bin/gui/icon-ide-16.xpm
myokit/_bin/gui/icon-ide-24.xpm
myokit/_bin/gui/icon-ide-256.xpm
myokit/_bin/gui/icon-ide-32.xpm
myokit/_bin/gui/icon-ide-48.xpm
myokit/_bin/gui/icon-ide-64.xpm
myokit/_bin/gui/icon-ide-96.xpm
myokit/_bin/gui/icon-ide.ico
myokit/_bin/gui/icon-ide.png
myokit/_bin/gui/new.png
myokit/_bin/gui/open.png
myokit/_bin/gui/redo.png
myokit/_bin/gui/run.png
myokit/_bin/gui/save.png
myokit/_bin/gui/undo.png
myokit/_bin/install-lin/myokit-datablock-viewer.desktop
myokit/_bin/install-lin/myokit-datalog-viewer.desktop
myokit/_bin/install-lin/myokit-ide.desktop
myokit/_bin/install-lin/myokit.lang
myokit/_bin/install-lin/x-abf.xml
myokit/_bin/install-lin/x-cellml.xml
myokit/_bin/install-lin/x-myokit.xml
myokit/_bin/install-lin/x-wcp.xml
myokit/_bin/install-win/menu.json
myokit/_bin/sundials-win-vs/LICENSE
myokit/_bin/sundials-win-vs/include/cvodes/cvodes.h
myokit/_bin/sundials-win-vs/include/cvodes/cvodes_direct.h
myokit/_bin/sundials-win-vs/include/cvodes/cvodes_ls.h
myokit/_bin/sundials-win-vs/include/nvector/nvector_serial.h
myokit-1.38.0.dist-info/LICENSE.txt
myokit-1.38.0.dist-info/METADATA
myokit-1.38.0.dist-info/WHEEL
myokit-1.38.0.dist-info/entry_points.txt
myokit-1.38.0.dist-info/top_level.txt
myokit-1.38.0.dist-info/RECORD
