Metadata-Version: 2.1
Name: myokit
Version: 1.38.0
Summary: A modeling and simulation tool for cardiac cellular electrophysiology
Home-page: http://myokit.org
Author: Michael Clerx
Author-email: michael@myokit.org
License: BSD 3-clause license
Project-URL: Bug Tracker, https://github.com/myokit/myokit/issues
Project-URL: Documentation, http://docs.myokit.org
Project-URL: Source Code, https://github.com/myokit/myokit
Classifier: Development Status :: 5 - Production/Stable
Classifier: Intended Audience :: Science/Research
Classifier: License :: OSI Approved :: BSD License
Classifier: Operating System :: OS Independent
Classifier: Programming Language :: Python :: 3
Classifier: Topic :: Scientific/Engineering
Classifier: Topic :: Scientific/Engineering :: Bio-Informatics
Classifier: Topic :: Scientific/Engineering :: Chemistry
Classifier: Topic :: Scientific/Engineering :: Mathematics
Classifier: Topic :: Scientific/Engineering :: Medical Science Apps.
Classifier: Topic :: Scientific/Engineering :: Physics
Requires-Python: >=3.7
License-File: LICENSE.txt
Requires-Dist: configparser
Requires-Dist: lxml
Requires-Dist: matplotlib>=2.2
Requires-Dist: numpy
Requires-Dist: setuptools
Provides-Extra: dev
Requires-Dist: coverage; extra == "dev"
Requires-Dist: flake8>=3; extra == "dev"
Provides-Extra: docs
Requires-Dist: sphinx>=1.7.4; extra == "docs"
Provides-Extra: gui
Requires-Dist: pyqt6; extra == "gui"
Requires-Dist: sip; extra == "gui"
Provides-Extra: optional
Requires-Dist: scipy; extra == "optional"
Requires-Dist: sympy; extra == "optional"
Provides-Extra: pyqt
Requires-Dist: pyqt6; extra == "pyqt"
Requires-Dist: sip; extra == "pyqt"
Provides-Extra: pyside
Requires-Dist: pyside6; extra == "pyside"
